mylib_chenzhang_kxd_test/Test.py
mylib_chenzhang_kxd_test/__init__.py
mylib_chenzhang_kxd_test-0.1.dist-info/DESCRIPTION.rst
mylib_chenzhang_kxd_test-0.1.dist-info/METADATA
mylib_chenzhang_kxd_test-0.1.dist-info/RECORD
mylib_chenzhang_kxd_test-0.1.dist-info/WHEEL
mylib_chenzhang_kxd_test-0.1.dist-info/metadata.json
mylib_chenzhang_kxd_test-0.1.dist-info/top_level.txt
