Metadata-Version: 2.0
Name: mylib-chenzhang-kxd-test
Version: 0.1
Summary: Django Basic Apps
Home-page: http://www.baidu.com
Author: zhangchen
Author-email: 374201603@qq.com
License: UNKNOWN
Platform: UNKNOWN
